<?xml version="1.0" encoding="UTF-8"?>
<ViewConfig>
  <Arguments/>
  <Context/>
  <Model>
    <DataType name="NoticeInfo">
      <Property name="creationType">com.mr.sa.entity.NoticeInfo</Property>
      <PropertyDef name="id">
        <Property name="dataType">String</Property>
      </PropertyDef>
      <PropertyDef name="name">
        <Property name="dataType">String</Property>
        <Property name="label">主题</Property>
      </PropertyDef>
      <PropertyDef name="type">
        <Property name="dataType">String</Property>
        <Property name="label">类型</Property>
        <Property name="mapping">
          <Property name="mapValues">${dorado.getDataProvider(&quot;enumProvider#getValues&quot;).getResult(&quot;NOTICE_TYPE&quot;)}</Property>
        </Property>
      </PropertyDef>
      <PropertyDef name="content">
        <Property name="dataType">String</Property>
        <Property name="label">内容</Property>
      </PropertyDef>
      <PropertyDef name="createdDate">
        <Property></Property>
        <Property name="label">创建日期</Property>
        <Property name="dataType">DateTime</Property>
      </PropertyDef>
      <PropertyDef name="creator">
        <Property></Property>
        <Property name="label">创建人</Property>
      </PropertyDef>
      <PropertyDef name="updateDate">
        <Property></Property>
        <Property name="label">修改日期</Property>
        <Property name="dataType">DateTime</Property>
      </PropertyDef>
      <PropertyDef name="modifier">
        <Property></Property>
        <Property name="label">修改人</Property>
      </PropertyDef>
    </DataType>
    <DataType name="Condition">
      <PropertyDef name="name">
        <Property name="dataType">String</Property>
        <Property name="label">名称</Property>
      </PropertyDef>
      <PropertyDef name="type">
        <Property name="dataType">String</Property>
        <Property name="label">类型</Property>
        <Property name="mapping">
          <Property name="mapValues">${dorado.getDataProvider(&quot;enumProvider#getValues&quot;).getResult(&quot;NOTICE_TYPE&quot;)}</Property>
        </Property>
      </PropertyDef>
      <PropertyDef name="content">
        <Property name="dataType">String</Property>
      </PropertyDef>
      <PropertyDef name="content">
        <Property name="dataType">String</Property>
        <Property name="label">内容</Property>
      </PropertyDef>
    </DataType>
    <DataType name="User">
      <Property name="creationType">com.mr.sa.entity.app.AppUser</Property>
      <PropertyDef name="checked">
        <Property name="dataType">boolean</Property>
        <Property name="label">是否选中</Property>
      </PropertyDef>
      <PropertyDef name="username">
        <Property></Property>
      </PropertyDef>
      <PropertyDef name="nickname">
        <Property></Property>
        <Property name="label">姓名</Property>
      </PropertyDef>
      <PropertyDef name="password">
        <Property></Property>
      </PropertyDef>
      <PropertyDef name="enabled">
        <Property name="dataType">boolean</Property>
      </PropertyDef>
      <PropertyDef name="roleId">
        <Property></Property>
        <Property name="label">角色</Property>
      </PropertyDef>
      <PropertyDef name="orgId">
        <Property></Property>
        <Property name="label">组织</Property>
      </PropertyDef>
      <PropertyDef name="gender">
        <Property></Property>
        <Property name="label">性别</Property>
      </PropertyDef>
      <PropertyDef name="phone">
        <Property></Property>
        <Property name="label">电话</Property>
      </PropertyDef>
      <PropertyDef name="mail">
        <Property></Property>
        <Property name="label">邮箱</Property>
      </PropertyDef>
      <PropertyDef name="address">
        <Property></Property>
        <Property name="label">住址</Property>
      </PropertyDef>
      <PropertyDef name="remark">
        <Property></Property>
        <Property name="label">备注</Property>
      </PropertyDef>
      <PropertyDef name="id">
        <Property></Property>
        <Property name="label">id</Property>
      </PropertyDef>
      <PropertyDef name="createdDate">
        <Property name="dataType">Date</Property>
        <Property name="label">创建日期</Property>
      </PropertyDef>
      <PropertyDef name="creator">
        <Property></Property>
        <Property name="label">创建人</Property>
      </PropertyDef>
      <PropertyDef name="updateDate">
        <Property name="dataType">Date</Property>
        <Property name="label">修改日期</Property>
      </PropertyDef>
      <PropertyDef name="modifier">
        <Property></Property>
        <Property name="label">修改人</Property>
      </PropertyDef>
      <PropertyDef name="avatar">
        <Property></Property>
        <Property name="label">头像</Property>
      </PropertyDef>
    </DataType>
    <DataType name="Org">
      <Property name="creationType">com.mr.sa.entity.Org</Property>
      <PropertyDef name="id">
        <Property></Property>
        <Property name="label">ID</Property>
      </PropertyDef>
      <PropertyDef name="code">
        <Property></Property>
        <Property name="label">编码</Property>
        <Property name="required">true</Property>
      </PropertyDef>
      <PropertyDef name="name">
        <Property></Property>
        <Property name="label">名称</Property>
      </PropertyDef>
      <PropertyDef name="parentId">
        <Property></Property>
      </PropertyDef>
      <PropertyDef name="longitude">
        <Property></Property>
        <Property name="label">经度</Property>
      </PropertyDef>
      <PropertyDef name="latitude">
        <Property></Property>
        <Property name="label">纬度</Property>
      </PropertyDef>
      <PropertyDef name="address">
        <Property></Property>
        <Property name="label">地址</Property>
      </PropertyDef>
      <Reference name="children">
        <ClientEvent name="beforeLoadData">var parameter=self.get(&quot;parameter&quot;);&#xD;
 var entity = view.get(&quot;#dsNotice&quot;).getData(&quot;#&quot;); &#xD;
var noticeId=entity.get(&quot;id&quot;);&#xD;
parameter.set(&quot;noticeId&quot;,noticeId);&#xD;
</ClientEvent>
        <Property name="dataType">[SELF]</Property>
        <Property name="dataProvider">saNoticeController#loadChildrenOrg</Property>
        <Property name="parameter">
          <Entity>
            <Property name="parentId">$${this.id}</Property>
          </Entity>
        </Property>
      </Reference>
      <PropertyDef name="checked">
        <Property name="dataType">boolean</Property>
      </PropertyDef>
    </DataType>
    <DataType name="OrgMain">
      <Property name="creationType">com.mr.sa.entity.Org</Property>
      <PropertyDef name="id">
        <Property></Property>
        <Property name="label">ID</Property>
      </PropertyDef>
      <PropertyDef name="code">
        <Property></Property>
        <Property name="label">编码</Property>
        <Property name="required">true</Property>
      </PropertyDef>
      <PropertyDef name="name">
        <Property></Property>
        <Property name="label">名称</Property>
      </PropertyDef>
      <PropertyDef name="parentId">
        <Property></Property>
      </PropertyDef>
      <PropertyDef name="longitude">
        <Property></Property>
        <Property name="label">经度</Property>
      </PropertyDef>
      <PropertyDef name="latitude">
        <Property></Property>
        <Property name="label">纬度</Property>
      </PropertyDef>
      <PropertyDef name="address">
        <Property></Property>
        <Property name="label">地址</Property>
      </PropertyDef>
      <Reference name="children">
        <ClientEvent name="beforeLoadData">var parameter=self.get(&quot;parameter&quot;);&#xD;
 var entity = view.get(&quot;#dsNotice&quot;).getData(&quot;#&quot;); &#xD;
var noticeId=entity.get(&quot;id&quot;);&#xD;
parameter.set(&quot;noticeId&quot;,noticeId);&#xD;
</ClientEvent>
        <Property name="dataType">[SELF]</Property>
        <Property name="dataProvider">saNoticeController#loadChildrenOrg</Property>
        <Property name="parameter">
          <Entity>
            <Property name="parentId">$${this.id}</Property>
          </Entity>
        </Property>
      </Reference>
      <PropertyDef name="checked">
        <ClientEvent name="onSet">var entity = view.get(&quot;#dgNotice&quot;).getCurrentItem();&#xD;
var noticeId = entity.get(&quot;id&quot;);&#xD;
var orgId = arg.entity.get(&quot;code&quot;);&#xD;
var paraSave = {&#xD;
	'noticeId': noticeId,&#xD;
	&quot;orgId&quot;: orgId&#xD;
}&#xD;
&#xD;
if (arg.value) {&#xD;
	view.get(&quot;#aaSaveOrg&quot;).set(&quot;parameter&quot;, paraSave).execute(function(result) {})&#xD;
	 &#xD;
} else {&#xD;
	view.get(&quot;#aaDeleteOrg&quot;).set(&quot;parameter&quot;, paraSave).execute(function(result) {&#xD;
	 &#xD;
	})&#xD;
}</ClientEvent>
        <Property name="dataType">boolean</Property>
      </PropertyDef>
    </DataType>
    <DataType name="SpecialTask">
      <Property name="creationType">com.mr.sa.entity.SpecialTask</Property>
      <PropertyDef name="id">
        <Property name="dataType">String</Property>
      </PropertyDef>
      <PropertyDef name="name">
        <Property name="dataType">String</Property>
        <Property name="label">任务名称</Property>
        <Property name="required">true</Property>
      </PropertyDef>
      <PropertyDef name="taskStartTime">
        <Property name="dataType">DateTime</Property>
        <Property name="label">任务开始时间</Property>
        <Property name="required">true</Property>
      </PropertyDef>
      <PropertyDef name="taskEndTime">
        <Property name="dataType">DateTime</Property>
        <Property name="label">任务结束时间</Property>
        <Property name="required">true</Property>
      </PropertyDef>
      <PropertyDef name="doneRatio">
        <Property name="dataType">Integer</Property>
        <Property name="label">完成比例(%)</Property>
        <Property name="required">true</Property>
      </PropertyDef>
      <PropertyDef name="createdDate">
        <Property></Property>
        <Property name="label">创建日期</Property>
        <Property name="dataType">DateTime</Property>
      </PropertyDef>
      <PropertyDef name="creator">
        <Property></Property>
        <Property name="label">创建人</Property>
      </PropertyDef>
      <PropertyDef name="updateDate">
        <Property></Property>
        <Property name="label">修改日期</Property>
        <Property name="dataType">DateTime</Property>
      </PropertyDef>
      <PropertyDef name="modifier">
        <Property></Property>
        <Property name="label">修改人</Property>
      </PropertyDef>
      <PropertyDef name="type">
        <Property></Property>
        <Property name="label">任务类型</Property>
        <Property name="mapping">
          <Property name="mapValues">${dorado.getDataProvider(&quot;specialTaskTypeController#getValuesName&quot;).getResult()}</Property>
        </Property>
      </PropertyDef>
      <PropertyDef name="integralTask">
        <Property name="dataType">boolean</Property>
        <Property name="label">积分增项任务</Property>
      </PropertyDef>
      <PropertyDef name="integralValue">
        <Property name="dataType">Integer</Property>
        <Property name="label">积分值</Property>
        <Property name="defaultValue">0</Property>
      </PropertyDef>
      <PropertyDef name="checked">
        <Property name="dataType">boolean</Property>
        <Property name="label">是否选中</Property>
      </PropertyDef>
    </DataType>
    <DataType name="NoticeRead">
      <Property name="creationType">com.mr.sa.entity.NoticeRead</Property>
      <PropertyDef name="noticeId">
        <Property></Property>
        <Property name="label">公告ID</Property>
      </PropertyDef>
      <PropertyDef name="userId">
        <Property></Property>
        <Property name="label">用户ID</Property>
      </PropertyDef>
      <PropertyDef name="orgId">
        <Property></Property>
        <Property name="label">组织ID</Property>
      </PropertyDef>
      <PropertyDef name="specialTaskId">
        <Property></Property>
        <Property name="label">专项任务ID</Property>
      </PropertyDef>
      <PropertyDef name="read">
        <Property name="dataType">boolean</Property>
        <Property name="label">是否已阅</Property>
      </PropertyDef>
      <PropertyDef name="id">
        <Property></Property>
        <Property name="label">id</Property>
      </PropertyDef>
      <PropertyDef name="createdDate">
        <Property name="dataType">Date</Property>
        <Property name="label">创建日期</Property>
      </PropertyDef>
      <PropertyDef name="creator">
        <Property></Property>
        <Property name="label">创建人</Property>
      </PropertyDef>
      <PropertyDef name="updateDate">
        <Property name="dataType">DateTime</Property>
        <Property name="label">阅读时间</Property>
      </PropertyDef>
      <PropertyDef name="modifier">
        <Property></Property>
        <Property name="label">修改人</Property>
      </PropertyDef>
      <PropertyDef name="user">
        <Property name="dataType">User</Property>
      </PropertyDef>
    </DataType>
  </Model>
  <View>
    <Property name="packages">font-awesome,colors,entypo</Property>
    <Property name="title">公告信息维护</Property>
    <Container id="ds">
      <DataSet id="dsNotice">
        <Property name="dataProvider">saNoticeController#query</Property>
        <Property name="pageSize">20</Property>
        <Property name="dataType">[NoticeInfo]</Property>
        <Property>lazy</Property>
      </DataSet>
      <DataSet id="dsOrg">
        <Property name="dataProvider">specialTaskController#loadOrg</Property>
        <Property name="dataType">[Org]</Property>
      </DataSet>
      <DataSet id="dsUser">
        <Property name="dataType">[User]</Property>
        <Property name="dataProvider">saNoticeController#queryUser</Property>
        <Property name="loadMode">manual</Property>
      </DataSet>
      <DataSet id="dsOrgMain">
        <ClientEvent name="beforeLoadData">var entity = view.get(&quot;#dsNotice&quot;).getData(&quot;#&quot;); &#xD;
var noticeId=entity.get(&quot;id&quot;);&#xD;
var paraQuery = {&#xD;
	'noticeId': noticeId&#xD;
}&#xD;
self.set(&quot;parameter&quot;, paraQuery);&#xD;
</ClientEvent>
        <Property name="dataProvider">saNoticeController#loadOrg</Property>
        <Property name="dataType">[OrgMain]</Property>
      </DataSet>
      <DataSet id="dsSpecialTask">
        <Property name="dataProvider">saNoticeController#querySpecialTask</Property>
        <Property name="dataType">[SpecialTask]</Property>
        <Property>lazy</Property>
      </DataSet>
      <DataSet id="dsNoticeRead">
        <ClientEvent name="beforeLoadData">var entity = view.get(&quot;#dsNotice&quot;).getData(&quot;#&quot;); &#xD;
var noticeId=entity.get(&quot;id&quot;);&#xD;
var paraQuery = {&#xD;
	'noticeId': noticeId&#xD;
}&#xD;
self.set(&quot;parameter&quot;, paraQuery);&#xD;
</ClientEvent>
        <Property name="dataProvider">noticeReadController#query</Property>
        <Property name="pageSize">20</Property>
        <Property name="dataType">[NoticeRead]</Property>
        <Property name="loadMode">manual</Property>
      </DataSet>
    </Container>
    <Container id="action">
      <AjaxAction id="aaSaveUser">
        <Property name="service">saNoticeService#saveUser</Property>
      </AjaxAction>
      <AjaxAction id="aaSaveOrg">
        <Property name="service">saNoticeService#saveOrg</Property>
        <Property name="async">false</Property>
      </AjaxAction>
      <AjaxAction id="aaDeleteOrg">
        <Property name="service">saNoticeService#deleteOrg</Property>
        <Property name="async">false</Property>
      </AjaxAction>
      <AjaxAction id="aaSaveSpecialTask">
        <Property name="service">saNoticeService#saveSpecialTask</Property>
      </AjaxAction>
      <UpdateAction id="updateAction">
        <Property name="successMessage">操作成功!</Property>
        <Property name="executingMessage">正在保存...</Property>
        <Property name="dataResolver">saNoticeController#save</Property>
        <UpdateItem>
          <Property name="dataSet">dsNotice</Property>
        </UpdateItem>
      </UpdateAction>
      <AjaxAction id="aaSetTop">
        <Property name="service">saNoticeService#setTop</Property>
        <Property name="async">false</Property>
      </AjaxAction>
      <AjaxAction id="aaSaveUserAll">
        <Property name="service">saNoticeService#saveUserAll</Property>
      </AjaxAction>
    </Container>
    <AutoForm id="formCondition">
      <ClientEvent name="onKeyDown">if (arg.keyCode === 13) {&#xD;
window.clearTimeout(self.urlQueryTimeout);&#xD;
self.urlQueryTimeout = window.setTimeout(function() {&#xD;
var data = view.get(&quot;#formCondition.entity&quot;);&#xD;
with (view.get(&quot;#dsNotice&quot;)) {&#xD;
set(&quot;parameter&quot;, data);&#xD;
flushAsync();&#xD;
}&#xD;
}, 250);&#xD;
}</ClientEvent>
      <Property name="labelWidth">100</Property>
      <Property name="cols">*,*,*,*</Property>
      <Property name="createPrivateDataSet">true</Property>
      <Property name="dataType">Condition</Property>
      <Property name="labelAlign">center</Property>
      <Property name="showHint">false</Property>
      <AutoFormElement>
        <Property name="name">name</Property>
        <Property name="label">名称</Property>
        <Editor/>
      </AutoFormElement>
      <AutoFormElement>
        <Property name="name">type</Property>
        <Property name="label">类型</Property>
        <Editor/>
      </AutoFormElement>
    </AutoForm>
    <ToolBar>
      <Property name="fixRight">true</Property>
      <ToolBarButton>
        <ClientEvent name="onClick">var data = view.get(&quot;#formCondition.entity&quot;);&#xD;
with (view.get(&quot;#dsNotice&quot;)){&#xD;
set(&quot;parameter&quot;, data);&#xD;
flushAsync();&#xD;
}</ClientEvent>
        <Property name="caption">查询</Property>
        <Property name="iconClass">fa fa-search</Property>
      </ToolBarButton>
      <ToolBarButton>
        <ClientEvent name="onClick">var datas = view.get(&quot;#dsNotice.data&quot;);&#xD;
datas.insert();&#xD;
view.get(&quot;#dialogNotice&quot;).show();&#xD;
arg.processDefault=false;</ClientEvent>
        <Property name="caption">新增</Property>
        <Property name="iconClass">fa fa-plus</Property>
      </ToolBarButton>
      <ToolBarButton>
        <ClientEvent name="onClick">var data=view.get(&quot;#dsNotice.data&quot;);&#xD;
if(data.current){&#xD;
view.get(&quot;#dialogNotice&quot;).show();&#xD;
}else{&#xD;
dorado.MessageBox.alert(&quot;当前表没有信息可供编辑!&quot;);&#xD;
}</ClientEvent>
        <Property name="caption">修改</Property>
        <Property name="iconClass">fa fa-pencil-square-o</Property>
      </ToolBarButton>
      <ToolBarButton>
        <ClientEvent name="onClick">var updateAction=view.get(&quot;#updateAction&quot;);&#xD;
var selection = view.get(&quot;#dgNotice&quot;).get(&quot;selection&quot;);&#xD;
&#xD;
if(0 != selection.length) {&#xD;
dorado.MessageBox.confirm(&quot;确认操作吗?&quot;,function(){&#xD;
&#xD;
for (var i = 0; i &lt; selection.length; i++) {&#xD;
var select = selection[i];&#xD;
select.remove();&#xD;
}&#xD;
&#xD;
updateAction.execute();&#xD;
view.get(&quot;#dsNotice&quot;).flushAsync(); &#xD;
})&#xD;
&#xD;
} else {&#xD;
dorado.MessageBox.alert(&quot;请选择需要操作的记录！&quot;);&#xD;
}&#xD;
&#xD;
&#xD;
</ClientEvent>
        <Property name="iconClass">fa fa-trash-o</Property>
        <Property name="caption">删除(批量)</Property>
      </ToolBarButton>
      <ToolBarButton>
        <ClientEvent name="onClick">var entity = view.get(&quot;#dsNotice&quot;).getData(&quot;#&quot;); 
var noticeId=entity.get(&quot;id&quot;);
var paraQuery = {
	'noticeId': noticeId
}
view.get(&quot;#dialogNoticeUser&quot;).show();
</ClientEvent>
        <Property name="caption">按人员</Property>
        <Property name="iconClass">fa fa-users</Property>
      </ToolBarButton>
      <ToolBarButton>
        <ClientEvent name="onClick">var entity = view.get(&quot;#dsNotice&quot;).getData(&quot;#&quot;); 
var noticeId=entity.get(&quot;id&quot;);
var paraQuery = {
	'noticeId': noticeId
}
var entity = view.get(&quot;#dsOrgMain&quot;).flushAsync();
view.get(&quot;#dialogNoticeOrg&quot;).show();
</ClientEvent>
        <Property name="caption">按组织</Property>
        <Property name="iconClass">fa fa-sitemap</Property>
      </ToolBarButton>
      <ToolBarButton>
        <ClientEvent name="onClick">var entity = view.get(&quot;#dsNotice&quot;).getData(&quot;#&quot;); 
var noticeId=entity.get(&quot;id&quot;);
var paraQuery = {
	'noticeId': noticeId
}
view.get(&quot;#dsSpecialTask&quot;).set(&quot;parameter&quot;, paraQuery).flushAsync();
view.get(&quot;#dialogNoticeSpecialTask&quot;).show();
</ClientEvent>
        <Property name="caption">按专项任务</Property>
        <Property name="iconClass">fa fa-calendar-o</Property>
      </ToolBarButton>
      <ToolBarButton>
        <ClientEvent name="onClick">view.get(&quot;#dsNoticeRead&quot;).flushAsync();
view.get(&quot;#dialogNoticeRead&quot;).show();</ClientEvent>
        <Property name="caption">阅读记录</Property>
        <Property name="iconClass">fa fa-share-alt</Property>
      </ToolBarButton>
      <Fill/>
      <DataPilot>
        <Property name="dataSet">dsNotice</Property>
        <Property name="itemCodes">pages,pageSize</Property>
      </DataPilot>
    </ToolBar>
    <DataGrid id="dgNotice">
      <ClientEvent name="onCreate">var OperationCellRendererDetail = $extend(dorado.widget.grid.SubControlCellRenderer, {&#xD;
    createSubControl: function(arg) {&#xD;
        var entity = arg.data;&#xD;
		var id=entity.get(&quot;id&quot;);&#xD;
        var container = new dorado.widget.Container({&#xD;
            layout: new dorado.widget.layout.HBoxLayout()&#xD;
        });&#xD;
        container.set(&quot;children&quot;, [new dorado.widget.Button({&#xD;
            iconClass: &quot;fa fa-caret-up&quot;,&#xD;
			tip:&quot;置顶&quot;,&#xD;
            onClick: function(self) {&#xD;
				entity.set(&quot;top&quot;,true);&#xD;
				entity.set(&quot;topTime&quot;,new Date());&#xD;
				view.get(&quot;#updateAction&quot;).execute(function(){&#xD;
					view.get(&quot;#dsNotice&quot;).flushAsync();&#xD;
				}); &#xD;
            }&#xD;
        }),&#xD;
		new dorado.widget.Button({&#xD;
            iconClass: &quot;fa fa-caret-down&quot;,&#xD;
			tip:&quot;取消置顶&quot;,&#xD;
            onClick: function(self) {&#xD;
				entity.set(&quot;top&quot;,false);&#xD;
				entity.set(&quot;topTime&quot;,null);&#xD;
				view.get(&quot;#updateAction&quot;).execute(function(){&#xD;
					view.get(&quot;#dsNotice&quot;).flushAsync();&#xD;
				}); &#xD;
            }&#xD;
        })&#xD;
		]);&#xD;
        return container;&#xD;
    },&#xD;
&#xD;
    refreshSubControl: function(container, arg) {&#xD;
        var children = container.get(&quot;children&quot;);&#xD;
    }&#xD;
});&#xD;
&#xD;
self.set(&quot;#setTop.renderer&quot;, new OperationCellRendererDetail());&#xD;
</ClientEvent>
      <Property name="dataSet">dsNotice</Property>
      <Property name="dataType">NoticeInfo</Property>
      <Property name="selectionMode">multiRows</Property>
      <Property name="readOnly">true</Property>
      <RowSelectorColumn/>
      <RowNumColumn/>
      <DataColumn>
        <Property name="caption">主题</Property>
        <Property name="property">name</Property>
        <Property name="align">center</Property>
        <Property name="name">主题</Property>
      </DataColumn>
      <DataColumn name="类型">
        <Property name="caption">类型</Property>
        <Property name="property">type</Property>
        <Property name="align">center</Property>
      </DataColumn>
      <DataColumn name="createdDate">
        <Property name="property">createdDate</Property>
        <Property name="align">center</Property>
      </DataColumn>
      <DataColumn name="creator">
        <Property name="property">creator</Property>
        <Property name="align">center</Property>
      </DataColumn>
    </DataGrid>
    <Dialog id="dialogNotice">
      <ClientEvent name="onClose">var data=view.get(&quot;#dsNotice&quot;).getData();&#xD;
data.cancel();&#xD;
</ClientEvent>
      <Property>true</Property>
      <Property name="maximizeable">true</Property>
      <Property name="width">1024</Property>
      <Property name="height">500</Property>
      <Property>true</Property>
      <Property>true</Property>
      <Property name="caption">详情</Property>
      <Property name="maximized">true</Property>
      <Buttons>
        <Button>
          <ClientEvent name="onClick">var data=view.get(&quot;#dsNotice&quot;).getData();
var dialog=view.get(&quot;#dialogNotice&quot;);
data.cancel();
dialog.hide();</ClientEvent>
          <Property name="caption">关闭</Property>
          <Property name="iconClass">fa fa-arrow-circle-o-left</Property>
          <Property name="ui">decline</Property>
        </Button>
        <Button>
          <ClientEvent name="onClick">var dialog=view.get(&quot;#dialogNotice&quot;);&#xD;
var action=view.get(&quot;#updateAction&quot;);&#xD;
action.execute(function(){&#xD;
dialog.hide();&#xD;
view.get(&quot;#dsNotice&quot;).flushAsync(); &#xD;
})</ClientEvent>
          <Property name="caption">确定</Property>
          <Property name="iconClass">fa fa-check-circle</Property>
          <Property name="ui">highlight</Property>
        </Button>
      </Buttons>
      <Children>
        <AutoForm>
          <Property name="labelWidth">100</Property>
          <Property name="dataSet">dsNotice</Property>
          <Property name="cols">*,*</Property>
          <Property name="labelAlign">center</Property>
          <Property name="showHint">false</Property>
          <Property name="showHintMessage">true</Property>
          <AutoFormElement name="name">
            <Property name="name">name</Property>
            <Property name="property">name</Property>
            <Property name="label">名称</Property>
            <Editor/>
          </AutoFormElement>
          <AutoFormElement name="type">
            <Property name="name">type</Property>
            <Property name="property">type</Property>
            <Property name="label">类型</Property>
            <Editor/>
          </AutoFormElement>
          <AutoFormElement layoutConstraint="colSpan:2" name="content">
            <Property name="name">content</Property>
            <Property name="property">content</Property>
            <Property name="label">内容</Property>
            <Editor>
              <UEditor>
                <ClientEvent name="onCreate">dorado.ueditor.registerMode(&quot;custom&quot;, [&#xD;
'source','undo','redo','fontsize','removeformat','formatmatch', 'bold','italic','underline','fontfamily','forecolor','backcolor','|','indent','justifyleft','justifycenter','justifyright','justifyjustify','rowspacingtop','rowspacingbottom','lineheight','customstyle','paragraph','|','insertorderedlist','insertunorderedlist','horizontal','|','link','unlink','inserttable','deletetable','insertparagraphbeforetable','insertrow','deleterow','insertcol','mergecells','mergeright','mergedown','splittocells','splittorows','splittocols','emotion','insertimage','insertvideo','|','selectall','cleardoc','preview','fullscreen'&#xD;
]);</ClientEvent>
                <Property name="mode">custom</Property>
                <Property name="property">content</Property>
                <Property name="height">800</Property>
              </UEditor>
            </Editor>
          </AutoFormElement>
        </AutoForm>
      </Children>
      <Tools/>
    </Dialog>
    <Dialog id="dialogNoticeUser">
      <ClientEvent name="onClose">var data=view.get(&quot;#dsNotice&quot;).getData();
data.cancel();</ClientEvent>
      <Property>true</Property>
      <Property name="maximizeable">true</Property>
      <Property name="width">1024</Property>
      <Property name="height">500</Property>
      <Property>true</Property>
      <Property>true</Property>
      <Property name="caption">选择发送对象:人员</Property>
      <Buttons>
        <Button>
          <ClientEvent name="onClick">var data=view.get(&quot;#dsNotice&quot;).getData();
var dialog=view.get(&quot;#dialogNoticeUser&quot;);
data.cancel();
dialog.hide();
</ClientEvent>
          <Property name="caption">关闭</Property>
          <Property name="iconClass">fa fa-arrow-circle-o-left</Property>
          <Property name="ui">decline</Property>
        </Button>
        <Button>
          <ClientEvent name="onClick">view.get(&quot;#dialogNoticeUser&quot;).hide();&#xD;
&#xD;
var entity = view.get(&quot;#dgNotice&quot;).getCurrentItem();&#xD;
var noticeId = entity.get(&quot;id&quot;);&#xD;
&#xD;
var dsUser=view.get(&quot;#dsUser&quot;).getData();&#xD;
&#xD;
var paraSave = {&#xD;
	'noticeId': noticeId,&#xD;
	'dsUser': dsUser&#xD;
}&#xD;
&#xD;
view.get(&quot;#aaSaveUser&quot;).set(&quot;parameter&quot;, paraSave).execute(function(result) {});</ClientEvent>
          <Property name="caption">确定</Property>
          <Property name="iconClass">fa fa-check-circle</Property>
          <Property name="ui">highlight</Property>
        </Button>
      </Buttons>
      <Children>
        <SplitPanel>
          <Property name="position">30%</Property>
          <MainControl>
            <Panel>
              <Buttons/>
              <Children>
                <ToolBar>
                  <ToolBarButton>
                    <ClientEvent name="onClick">var dsUser=view.get(&quot;#dsUser&quot;).getData();&#xD;
dsUser.each(function(entity){&#xD;
	entity.set(&quot;checked&quot;,self.get(&quot;toggled&quot;))&#xD;
}); </ClientEvent>
                    <Property name="caption">勾选当前组织下所有用户</Property>
                    <Property name="iconClass">fa fa-check</Property>
                    <Property name="toggleable">true</Property>
                    <Property name="tags">op</Property>
                  </ToolBarButton>
                  <Separator/>
                  <ToolBarButton>
                    <ClientEvent name="onClick">view.get(&quot;#dialogNoticeUser&quot;).hide();

var entity = view.get(&quot;#dgNotice&quot;).getCurrentItem();
var noticeId = entity.get(&quot;id&quot;);

var paraSave = {
	'noticeId': noticeId
}

view.get(&quot;#aaSaveUserAll&quot;).set(&quot;parameter&quot;, paraSave).execute(function(result) {});</ClientEvent>
                    <Property name="caption">全员发送</Property>
                    <Property name="iconClass">fa fa-users</Property>
                  </ToolBarButton>
                </ToolBar>
                <DataGrid>
                  <Property name="dataSet">dsUser</Property>
                  <Property>clientSide</Property>
                  <Property>clientSide</Property>
                  <Property name="highlightCurrentRow">false</Property>
                  <RowNumColumn>
                    <Property name="width">60</Property>
                  </RowNumColumn>
                  <DataColumn>
                    <Property name="property">checked</Property>
                    <Property name="align">center</Property>
                    <Property name="name">checked</Property>
                  </DataColumn>
                  <DataColumn>
                    <ClientEvent name="onRenderCell">$(arg.dom).empty().xCreate(&#xD;
			{&#xD;
				tagName : &quot;IMG&quot;,&#xD;
				src : arg.data.get(&quot;avatar&quot;),&#xD;
				//style : &quot;margin: 2px&quot;&#xD;
				style : &quot;width: 30px; height: 30px; margin: 1px&quot;&#xD;
			});&#xD;
&#xD;
	dorado.TipManager.initTip(arg.dom.parentNode, {&#xD;
		content : {&#xD;
			tagName : &quot;IMG&quot;,&#xD;
			src : arg.data.get(&quot;avatar&quot;),&#xD;
			style : &quot;width: 120px; height: 120px; margin: 2px&quot;&#xD;
		},&#xD;
		arrowDirection : &quot;top&quot;,&#xD;
		arrowAlign : &quot;left&quot;&#xD;
	});</ClientEvent>
                    <Property name="property">avatar</Property>
                    <Property name="align">center</Property>
                    <Property name="caption">头像</Property>
                    <Property name="width">80</Property>
                    <Property name="name">avatar</Property>
                  </DataColumn>
                  <DataColumn>
                    <Property name="property">nickname</Property>
                    <Property name="name">nickname</Property>
                    <Property name="align">center</Property>
                    <Property name="readOnly">true</Property>
                  </DataColumn>
                  <DataColumn name="gender">
                    <Property name="property">gender</Property>
                    <Property name="align">center</Property>
                    <Property name="readOnly">true</Property>
                  </DataColumn>
                  <DataColumn name="phone">
                    <Property name="property">phone</Property>
                    <Property name="align">center</Property>
                    <Property name="readOnly">true</Property>
                  </DataColumn>
                </DataGrid>
              </Children>
              <Tools/>
            </Panel>
          </MainControl>
          <SideControl>
            <Container>
              <ToolBar>
                <Property name="fixRight">true</Property>
                <ToolBarLabel>
                  <Property name="text">选择组织</Property>
                  <Property name="exClassName">blue-text</Property>
                </ToolBarLabel>
                <Fill/>
                <Tip>
                  <Property name="floating">false</Property>
                  <Property name="text">点击组织联动发送人员</Property>
                </Tip>
              </ToolBar>
              <DataTree id="dtOrg" layoutConstraint="padding:15">
                <ClientEvent name="onRenderNode">var data = arg.node.get(&quot;data&quot;);
//var icon = data.get(&quot;icon&quot;) || &quot;&quot;;

var icon='fa fa-building yellow-text';
arg.node.set(&quot;iconClass&quot;, icon);
$(arg.dom).text(data.get(&quot;name&quot;) || &quot;&quot;);
</ClientEvent>
                <ClientEvent name="onDataRowClick">var node=view.get(&quot;#dtOrg&quot;).getCurrentItem().get(&quot;data&quot;);&#xD;
var orgId=node.get(&quot;code&quot;);&#xD;
var entity = view.get(&quot;#dsNotice&quot;).getData(&quot;#&quot;); &#xD;
var noticeId=entity.get(&quot;id&quot;);&#xD;
var paraUser={&#xD;
	&quot;orgId&quot;:orgId,&#xD;
	&quot;noticeId&quot;:noticeId&#xD;
}&#xD;
&#xD;
view.get(&quot;#dsUser&quot;).set(&quot;parameter&quot;, paraUser).flushAsync();&#xD;
</ClientEvent>
                <Property name="dataSet">dsOrg</Property>
                <Property name="currentNodeDataPath">currentNode</Property>
                <Property name="showLines">true</Property>
                <Property name="selectionMode">singleRow</Property>
                <Property name="useNativeScrollbars">true</Property>
                <Property name="allowNoCurrent">true</Property>
                <BindingConfigs>
                  <BindingConfig>
                    <Property name="childrenProperty">children</Property>
                    <Property name="labelProperty">name</Property>
                    <Property name="recursive">true</Property>
                    <Property name="tipProperty">address</Property>
                    <Property name="name">code</Property>
                    <Property name="checkedProperty">checked</Property>
                    <Property name="autoCheckChildren">false</Property>
                  </BindingConfig>
                </BindingConfigs>
              </DataTree>
            </Container>
          </SideControl>
        </SplitPanel>
      </Children>
      <Tools/>
    </Dialog>
    <Dialog id="dialogNoticeOrg">
      <ClientEvent name="onClose">var data=view.get(&quot;#dsNotice&quot;).getData();
data.cancel();
</ClientEvent>
      <Property>true</Property>
      <Property name="maximizeable">true</Property>
      <Property name="width">1024</Property>
      <Property name="height">500</Property>
      <Property>true</Property>
      <Property>true</Property>
      <Property name="caption">选择发送对象:组织</Property>
      <Buttons>
        <Button>
          <ClientEvent name="onClick">var data=view.get(&quot;#dsNotice&quot;).getData();
var dialog=view.get(&quot;#dialogNoticeOrg&quot;);
data.cancel();
dialog.hide();
</ClientEvent>
          <Property name="caption">关闭</Property>
          <Property name="iconClass">fa fa-arrow-circle-o-left</Property>
          <Property name="ui">decline</Property>
        </Button>
      </Buttons>
      <Children>
        <ToolBar>
          <ToolBarLabel>
            <Property name="text">选择组织</Property>
            <Property name="exClassName">blue-text</Property>
          </ToolBarLabel>
        </ToolBar>
        <DataTree id="dtOrgMain" layoutConstraint="padding:15">
          <ClientEvent name="onRenderNode">var data = arg.node.get(&quot;data&quot;);
//var icon = data.get(&quot;icon&quot;) || &quot;&quot;;

var icon='fa fa-building yellow-text';
arg.node.set(&quot;iconClass&quot;, icon);
$(arg.dom).text(data.get(&quot;name&quot;) || &quot;&quot;);
</ClientEvent>
          <Property name="dataSet">dsOrgMain</Property>
          <Property name="currentNodeDataPath">currentNode</Property>
          <Property name="showLines">true</Property>
          <Property name="selectionMode">singleRow</Property>
          <Property name="useNativeScrollbars">true</Property>
          <Property name="allowNoCurrent">true</Property>
          <BindingConfigs>
            <BindingConfig>
              <Property name="childrenProperty">children</Property>
              <Property name="labelProperty">name</Property>
              <Property name="recursive">true</Property>
              <Property name="tipProperty">address</Property>
              <Property name="name">code</Property>
              <Property name="checkedProperty">checked</Property>
              <Property name="autoCheckChildren">false</Property>
              <Property name="checkable">true</Property>
            </BindingConfig>
          </BindingConfigs>
        </DataTree>
      </Children>
      <Tools/>
    </Dialog>
    <Dialog id="dialogNoticeSpecialTask">
      <ClientEvent name="onClose">var data=view.get(&quot;#dsNotice&quot;).getData();
data.cancel();
</ClientEvent>
      <Property>true</Property>
      <Property name="maximizeable">true</Property>
      <Property name="width">1024</Property>
      <Property name="height">500</Property>
      <Property>true</Property>
      <Property>true</Property>
      <Property name="caption">选择发送对象:专项任务</Property>
      <Buttons>
        <Button>
          <ClientEvent name="onClick">var data=view.get(&quot;#dsNotice&quot;).getData();
var dialog=view.get(&quot;#dialogNoticeSpecialTask&quot;);
data.cancel();
dialog.hide();
</ClientEvent>
          <Property name="caption">关闭</Property>
          <Property name="iconClass">fa fa-arrow-circle-o-left</Property>
          <Property name="ui">decline</Property>
        </Button>
        <Button>
          <ClientEvent name="onClick">view.get(&quot;#dialogNoticeSpecialTask&quot;).hide();&#xD;
&#xD;
var entity = view.get(&quot;#dgNotice&quot;).getCurrentItem();&#xD;
var noticeId = entity.get(&quot;id&quot;);&#xD;
&#xD;
var dsSpecialTask=view.get(&quot;#dsSpecialTask&quot;).getData();&#xD;
&#xD;
var paraSave = {&#xD;
	'noticeId': noticeId,&#xD;
	'dsSpecialTask': dsSpecialTask&#xD;
}&#xD;
&#xD;
view.get(&quot;#aaSaveSpecialTask&quot;).set(&quot;parameter&quot;, paraSave).execute(function(result) {});</ClientEvent>
          <Property name="caption">确定</Property>
          <Property name="iconClass">fa fa-check-circle</Property>
          <Property name="ui">highlight</Property>
        </Button>
      </Buttons>
      <Children>
        <DataGrid id="dgSpecialTask">
          <Property name="dataSet">dsSpecialTask</Property>
          <Property name="dataType">SpecialTask</Property>
          <Property name="selectionMode">multiRows</Property>
          <Property name="highlightCurrentRow">false</Property>
          <RowNumColumn/>
          <DataColumn>
            <Property name="property">checked</Property>
            <Property name="align">center</Property>
            <Property name="name">checked</Property>
          </DataColumn>
          <DataColumn name="任务名称">
            <Property name="caption">任务名称</Property>
            <Property name="property">name</Property>
            <Property name="align">center</Property>
            <Property name="readOnly">true</Property>
          </DataColumn>
          <DataColumn>
            <Property name="property">type</Property>
            <Property name="name">任务类型</Property>
            <Property name="readOnly">true</Property>
            <Property name="align">center</Property>
          </DataColumn>
          <DataColumn name="任务开始时间">
            <Property name="caption">任务开始时间</Property>
            <Property name="property">taskStartTime</Property>
            <Property name="align">center</Property>
            <Property name="readOnly">true</Property>
          </DataColumn>
          <DataColumn name="任务结束时间">
            <Property name="caption">任务结束时间</Property>
            <Property name="property">taskEndTime</Property>
            <Property name="align">center</Property>
            <Property name="readOnly">true</Property>
          </DataColumn>
          <DataColumn name="完成比例(%)">
            <Property name="caption">完成比例(%)</Property>
            <Property name="property">doneRatio</Property>
            <Property name="align">center</Property>
            <Property name="readOnly">true</Property>
          </DataColumn>
          <DataColumn name="integralTask">
            <Property name="property">integralTask</Property>
            <Property name="align">center</Property>
            <Property name="readOnly">true</Property>
          </DataColumn>
          <DataColumn name="integralValue">
            <Property name="property">integralValue</Property>
            <Property name="align">center</Property>
            <Property name="readOnly">true</Property>
          </DataColumn>
        </DataGrid>
      </Children>
      <Tools/>
    </Dialog>
    <Dialog id="dialogNoticeRead">
      <ClientEvent name="onClose">var data=view.get(&quot;#dsNoticeRead&quot;).getData();&#xD;
data.cancel();&#xD;
</ClientEvent>
      <Property>true</Property>
      <Property name="maximizeable">true</Property>
      <Property name="width">1024</Property>
      <Property name="height">500</Property>
      <Property>true</Property>
      <Property>true</Property>
      <Property name="caption">阅读记录</Property>
      <Buttons>
        <Button>
          <ClientEvent name="onClick">var data=view.get(&quot;#dsNoticeRead&quot;).getData();
var dialog=view.get(&quot;#dialogNoticeRead&quot;);
data.cancel();
dialog.hide();</ClientEvent>
          <Property name="caption">关闭</Property>
          <Property name="iconClass">fa fa-arrow-circle-o-left</Property>
          <Property name="ui">decline</Property>
        </Button>
      </Buttons>
      <Children>
        <ToolBar>
          <Property name="fixRight">true</Property>
          <Fill/>
          <DataPilot>
            <Property name="dataSet">dsNoticeRead</Property>
            <Property name="itemCodes">pages,pageSize</Property>
          </DataPilot>
        </ToolBar>
        <DataGrid id="dgNoticeRead">
          <Property name="dataSet">dsNoticeRead</Property>
          <Property name="selectionMode">multiRows</Property>
          <Property name="readOnly">true</Property>
          <RowNumColumn/>
          <DataColumn name="userId">
            <Property name="property">userId</Property>
            <Property name="caption">人员ID</Property>
            <Property name="align">center</Property>
          </DataColumn>
          <DataColumn>
            <Property name="property">user.nickname</Property>
            <Property name="caption">人员名称</Property>
            <Property name="align">center</Property>
          </DataColumn>
          <DataColumn>
            <ClientEvent name="onRenderCell">$(arg.dom).empty().xCreate(&#xD;
			{&#xD;
				tagName : &quot;IMG&quot;,&#xD;
				src : arg.data.get(&quot;user.avatar&quot;),&#xD;
				//style : &quot;margin: 2px&quot;&#xD;
				style : &quot;width: 30px; height: 30px; margin: 1px&quot;&#xD;
			});&#xD;
&#xD;
	dorado.TipManager.initTip(arg.dom.parentNode, {&#xD;
		content : {&#xD;
			tagName : &quot;IMG&quot;,&#xD;
			src : arg.data.get(&quot;user.avatar&quot;),&#xD;
			style : &quot;width: 120px; height: 120px; margin: 2px&quot;&#xD;
		},&#xD;
		arrowDirection : &quot;top&quot;,&#xD;
		arrowAlign : &quot;left&quot;&#xD;
	});</ClientEvent>
            <Property name="property">user.avatar</Property>
            <Property name="align">center</Property>
            <Property name="caption">头像</Property>
            <Property name="width">80</Property>
            <Property name="name">avatar</Property>
          </DataColumn>
          <DataColumn name="read">
            <Property name="property">read</Property>
            <Property name="align">center</Property>
          </DataColumn>
          <DataColumn>
            <Property name="property">updateDate</Property>
            <Property name="name">updateDate</Property>
            <Property name="align">center</Property>
          </DataColumn>
        </DataGrid>
      </Children>
      <Tools/>
    </Dialog>
  </View>
</ViewConfig>
